[{"level": 1, "capacity": 5, "tiers": 3, "mergeN": 4, "wallets": [[1, 1, 0, 0], [0, 0, 1, 0], [], []], "par": 3}, {"level": 2, "capacity": 5, "tiers": 3, "mergeN": 4, "wallets": [[0, 1, 0, 0], [1, 0, 0, 0], [], [], []], "par": 3}, {"level": 3, "capacity": 5, "tiers": 3, "mergeN": 4, "wallets": [[0, 0, 0, 0], [0, 1, 0, 0], [], []], "par": 2}, {"level": 4, "capacity": 5, "tiers": 3, "mergeN": 4, "wallets": [[0, 0, 1, 0], [0, 0, 0, 0], [], [], []], "par": 2}, {"level": 5, "capacity": 5, "tiers": 3, "mergeN": 4, "wallets": [[0, 1, 0, 0], [1, 0, 0, 0], [], []], "par": 3}, {"level": 6, "capacity": 5, "tiers": 3, "mergeN": 4, "wallets": [[0, 0, 0, 0], [0, 1, 0, 0], [], [], []], "par": 2}, {"level": 7, "capacity": 5, "tiers": 3, "mergeN": 4, "wallets": [[1, 0, 0, 0], [0, 0, 1, 0], [], []], "par": 2}, {"level": 8, "capacity": 5, "tiers": 3, "mergeN": 4, "wallets": [[1, 0, 0, 0], [0, 1, 0, 1], [], [], []], "par": 3}, {"level": 9, "capacity": 5, "tiers": 3, "mergeN": 4, "wallets": [[1, 1, 0, 0], [0, 0, 1, 0], [], []], "par": 3}, {"level": 10, "capacity": 5, "tiers": 3, "mergeN": 4, "wallets": [[1, 0, 1, 0], [0, 0, 0, 0], [], [], []], "par": 3}, {"level": 11, "capacity": 5, "tiers": 3, "mergeN": 4, "wallets": [[1, 0, 0, 1], [0, 0, 1, 0], [], []], "par": 4}, {"level": 12, "capacity": 5, "tiers": 3, "mergeN": 4, "wallets": [[0, 1, 0, 0], [1, 0, 0, 0], [], [], []], "par": 3}, {"level": 13, "capacity": 5, "tiers": 3, "mergeN": 4, "wallets": [[0, 0, 1, 0], [0, 1, 0, 0], [], []], "par": 4}, {"level": 14, "capacity": 5, "tiers": 3, "mergeN": 4, "wallets": [[0, 0, 1, 0], [0, 0, 0, 1], [], [], []], "par": 3}, {"level": 15, "capacity": 5, "tiers": 3, "mergeN": 4, "wallets": [[1, 0, 0, 0], [0, 1, 0, 0], [], []], "par": 3}, {"level": 16, "capacity": 5, "tiers": 3, "mergeN": 4, "wallets": [[0, 0, 0, 1], [0, 1, 0, 0], [], [], []], "par": 3}, {"level": 17, "capacity": 5, "tiers": 3, "mergeN": 4, "wallets": [[0, 0, 1, 0], [0, 1, 0, 0], [], []], "par": 4}, {"level": 18, "capacity": 5, "tiers": 3, "mergeN": 4, "wallets": [[0, 0, 1, 0], [0, 1, 0, 0], [], [], []], "par": 4}, {"level": 19, "capacity": 5, "tiers": 3, "mergeN": 4, "wallets": [[0, 1, 0, 0], [0, 0, 1, 0], [], []], "par": 4}, {"level": 20, "capacity": 5, "tiers": 3, "mergeN": 4, "wallets": [[0, 0, 1, 0], [0, 1, 0, 0], [], [], []], "par": 4}, {"level": 21, "capacity": 5, "tiers": 3, "mergeN": 4, "wallets": [[0, 1, 0, 1], [0, 0, 1, 0], [], []], "par": 5}, {"level": 22, "capacity": 5, "tiers": 3, "mergeN": 4, "wallets": [[0, 0, 1, 0], [0, 0, 1, 0], [], [], []], "par": 4}, {"level": 23, "capacity": 5, "tiers": 3, "mergeN": 4, "wallets": [[0, 0, 1, 0], [1, 0, 0, 1], [], []], "par": 4}, {"level": 24, "capacity": 5, "tiers": 3, "mergeN": 4, "wallets": [[0, 0, 1, 0], [0, 1, 0, 0], [], [], []], "par": 4}, {"level": 25, "capacity": 5, "tiers": 3, "mergeN": 4, "wallets": [[1, 0, 1, 0], [0, 0, 1, 0], [], []], "par": 5}, {"level": 26, "capacity": 5, "tiers": 3, "mergeN": 4, "wallets": [[0, 1, 0, 1], [1, 0, 0, 1], [], [], []], "par": 5}, {"level": 27, "capacity": 5, "tiers": 3, "mergeN": 4, "wallets": [[0, 0, 1, 0], [1, 0, 1, 0], [], []], "par": 5}, {"level": 28, "capacity": 5, "tiers": 3, "mergeN": 4, "wallets": [[0, 0, 1, 0], [1, 0, 1, 0], [], [], []], "par": 5}, {"level": 29, "capacity": 5, "tiers": 3, "mergeN": 4, "wallets": [[0, 1, 0, 1], [0, 0, 1, 0], [], []], "par": 5}, {"level": 30, "capacity": 5, "tiers": 3, "mergeN": 4, "wallets": [[0, 0, 1, 0], [1, 0, 1, 0], [], [], []], "par": 5}, {"level": 31, "capacity": 6, "tiers": 3, "mergeN": 4, "wallets": [[0, 0, 0, 1, 0], [0, 1, 0, 1, 0], [0, 0, 0, 0, 0], [], []], "par": 6}, {"level": 32, "capacity": 6, "tiers": 3, "mergeN": 4, "wallets": [[0, 0, 1, 1, 0], [1, 0, 0, 0, 0], [0, 0, 1, 1, 0], [], []], "par": 5}, {"level": 33, "capacity": 6, "tiers": 3, "mergeN": 4, "wallets": [[0, 0, 0, 1, 1], [0, 0, 1, 0, 0], [0, 1, 0, 0, 0], [], []], "par": 5}, {"level": 34, "capacity": 6, "tiers": 3, "mergeN": 4, "wallets": [[1, 0, 0, 1, 0], [0, 0, 0, 0, 0], [0, 1, 1, 0, 1], [], []], "par": 5}, {"level": 35, "capacity": 6, "tiers": 3, "mergeN": 4, "wallets": [[0, 0, 1, 0, 0], [0, 1, 0, 0, 1], [0, 0, 1, 1, 1], [], []], "par": 5}, {"level": 36, "capacity": 6, "tiers": 3, "mergeN": 4, "wallets": [[0, 0, 1, 0, 0], [0, 0, 1, 0, 1], [0, 1, 0, 1, 0], [], []], "par": 8}, {"level": 37, "capacity": 6, "tiers": 3, "mergeN": 4, "wallets": [[0, 0, 1, 0, 0], [0, 0, 0, 0, 0], [0, 1, 1, 0, 1], [], []], "par": 5}, {"level": 38, "capacity": 6, "tiers": 3, "mergeN": 4, "wallets": [[0, 0, 1, 0, 0], [0, 1, 0, 0, 0], [0, 0, 0, 1, 1], [], []], "par": 5}, {"level": 39, "capacity": 6, "tiers": 3, "mergeN": 4, "wallets": [[0, 0, 0, 1, 0], [0, 1, 0, 0, 0], [0, 1, 0, 0, 0], [], []], "par": 5}, {"level": 40, "capacity": 6, "tiers": 3, "mergeN": 4, "wallets": [[0, 0, 1, 0, 0], [0, 0, 0, 1, 0], [0, 0, 1, 0, 0], [], []], "par": 6}, {"level": 41, "capacity": 6, "tiers": 3, "mergeN": 4, "wallets": [[0, 0, 1, 0, 0], [1, 1, 0, 1, 0], [1, 0, 0, 0, 0], [], []], "par": 5}, {"level": 42, "capacity": 6, "tiers": 3, "mergeN": 4, "wallets": [[1, 0, 0, 0, 0], [0, 1, 0, 0, 1], [1, 0, 0, 1, 0], [], []], "par": 6}, {"level": 43, "capacity": 6, "tiers": 3, "mergeN": 4, "wallets": [[0, 1, 1, 0, 0], [0, 0, 1, 0, 0], [1, 0, 0, 0, 0], [], []], "par": 5}, {"level": 44, "capacity": 6, "tiers": 3, "mergeN": 4, "wallets": [[1, 0, 1, 0, 0], [0, 0, 0, 1, 0], [0, 0, 1, 1, 0], [], []], "par": 7}, {"level": 45, "capacity": 6, "tiers": 3, "mergeN": 4, "wallets": [[0, 0, 1, 0, 0], [0, 0, 0, 1, 0], [0, 0, 1, 0, 0], [], []], "par": 6}, {"level": 46, "capacity": 6, "tiers": 3, "mergeN": 4, "wallets": [[0, 1, 0, 0, 0], [0, 0, 0, 1, 0], [0, 0, 1, 0, 0], [], []], "par": 5}, {"level": 47, "capacity": 6, "tiers": 3, "mergeN": 4, "wallets": [[0, 0, 0, 0, 1], [1, 0, 0, 0, 1], [0, 1, 0, 0, 1], [], []], "par": 6}, {"level": 48, "capacity": 6, "tiers": 3, "mergeN": 4, "wallets": [[0, 1, 0, 0, 1], [0, 0, 0, 1, 0], [0, 0, 0, 0, 0], [], []], "par": 5}, {"level": 49, "capacity": 6, "tiers": 3, "mergeN": 4, "wallets": [[0, 1, 1, 0, 0], [0, 0, 0, 0, 0], [0, 1, 0, 1, 1], [], []], "par": 5}, {"level": 50, "capacity": 6, "tiers": 3, "mergeN": 4, "wallets": [[0, 1, 0, 0, 0], [0, 0, 1, 0, 0], [0, 0, 0, 1, 0], [], []], "par": 5}, {"level": 51, "capacity": 6, "tiers": 3, "mergeN": 4, "wallets": [[0, 0, 0, 1, 0], [0, 0, 1, 1, 0], [0, 0, 1, 1, 1], [], []], "par": 5}, {"level": 52, "capacity": 6, "tiers": 3, "mergeN": 4, "wallets": [[0, 0, 0, 0, 0], [0, 0, 1, 1, 0], [1, 0, 1, 0, 0], [], []], "par": 5}, {"level": 53, "capacity": 6, "tiers": 3, "mergeN": 4, "wallets": [[0, 0, 1, 0, 0], [0, 1, 0, 0, 0], [1, 0, 0, 0, 0], [], []], "par": 5}, {"level": 54, "capacity": 6, "tiers": 3, "mergeN": 4, "wallets": [[0, 1, 0, 0, 0], [1, 0, 0, 0, 0], [0, 0, 1, 0, 0], [], []], "par": 5}, {"level": 55, "capacity": 6, "tiers": 3, "mergeN": 4, "wallets": [[0, 0, 1, 0, 0], [0, 0, 1, 0, 0], [0, 1, 1, 0, 0], [], []], "par": 6}, {"level": 56, "capacity": 6, "tiers": 3, "mergeN": 4, "wallets": [[0, 0, 0, 0, 1], [0, 1, 0, 0, 0], [0, 1, 0, 1, 0], [], []], "par": 6}, {"level": 57, "capacity": 6, "tiers": 3, "mergeN": 4, "wallets": [[0, 0, 0, 0, 1], [0, 1, 0, 0, 1], [0, 1, 0, 0, 0], [], []], "par": 6}, {"level": 58, "capacity": 6, "tiers": 3, "mergeN": 4, "wallets": [[0, 0, 1, 0, 0], [0, 0, 1, 0, 1], [0, 0, 0, 0, 1], [], []], "par": 6}, {"level": 59, "capacity": 6, "tiers": 3, "mergeN": 4, "wallets": [[0, 0, 1, 1, 0], [0, 0, 0, 1, 0], [0, 0, 0, 1, 0], [], []], "par": 6}, {"level": 60, "capacity": 6, "tiers": 3, "mergeN": 4, "wallets": [[0, 0, 0, 1, 0], [0, 0, 1, 0, 0], [0, 1, 0, 0, 0], [], []], "par": 5}, {"level": 61, "capacity": 6, "tiers": 3, "mergeN": 4, "wallets": [[0, 1, 0, 0, 0], [1, 0, 0, 0, 0], [1, 0, 0, 0, 1], [], []], "par": 5}, {"level": 62, "capacity": 6, "tiers": 3, "mergeN": 4, "wallets": [[1, 0, 0, 0, 0], [0, 0, 1, 0, 0], [0, 1, 0, 0, 1], [], []], "par": 5}, {"level": 63, "capacity": 6, "tiers": 3, "mergeN": 4, "wallets": [[0, 1, 0, 0, 1], [0, 0, 1, 1, 0], [1, 0, 0, 0, 0], [], []], "par": 6}, {"level": 64, "capacity": 6, "tiers": 3, "mergeN": 4, "wallets": [[0, 0, 1, 0, 0], [0, 0, 0, 1, 0], [1, 0, 0, 0, 0], [], []], "par": 5}, {"level": 65, "capacity": 6, "tiers": 3, "mergeN": 4, "wallets": [[1, 0, 0, 1, 0], [1, 0, 0, 0, 0], [1, 0, 0, 0, 0], [], []], "par": 6}, {"level": 66, "capacity": 6, "tiers": 3, "mergeN": 4, "wallets": [[0, 0, 1, 0, 0], [0, 0, 1, 0, 0], [1, 0, 0, 0, 1], [], []], "par": 6}, {"level": 67, "capacity": 6, "tiers": 3, "mergeN": 4, "wallets": [[0, 0, 0, 0, 1, 0], [1, 0, 1, 0, 1, 0], [0, 0, 1, 0, 0, 0], [], []], "par": 8}, {"level": 68, "capacity": 6, "tiers": 3, "mergeN": 4, "wallets": [[0, 1, 0, 0, 1, 0], [0, 1, 0, 1, 0, 0], [1, 1, 0, 0, 1, 1], [], [], []], "par": 8}, {"level": 69, "capacity": 6, "tiers": 3, "mergeN": 4, "wallets": [[1, 0, 0, 0, 0, 1], [0, 0, 1, 0, 1, 0], [0, 0, 0, 1, 0, 0], [], []], "par": 8}, {"level": 70, "capacity": 6, "tiers": 3, "mergeN": 4, "wallets": [[0, 1, 0, 0, 1, 0], [1, 0, 0, 0, 0, 1], [1, 0, 0, 1, 0, 0], [], [], []], "par": 8}, {"level": 71, "capacity": 6, "tiers": 3, "mergeN": 4, "wallets": [[0, 0, 0, 0, 0, 1], [0, 1, 0, 1, 0, 1], [1, 0, 1, 0, 0, 0], [], []], "par": 8}, {"level": 72, "capacity": 6, "tiers": 3, "mergeN": 4, "wallets": [[1, 0, 1, 1, 0, 0], [0, 0, 1, 0, 0, 1], [0, 0, 0, 1, 0, 0], [], [], []], "par": 8}, {"level": 73, "capacity": 6, "tiers": 3, "mergeN": 4, "wallets": [[1, 1, 0, 1, 0, 1], [0, 0, 0, 1, 0, 1], [0, 0, 0, 1, 0, 1], [], []], "par": 9}, {"level": 74, "capacity": 6, "tiers": 3, "mergeN": 4, "wallets": [[0, 1, 0, 0, 0, 0], [0, 0, 0, 1, 0, 1], [0, 0, 1, 0, 1, 0], [], [], []], "par": 9}, {"level": 75, "capacity": 6, "tiers": 3, "mergeN": 4, "wallets": [[0, 0, 1, 0, 1, 0], [1, 0, 0, 0, 0, 1], [0, 0, 0, 0, 1, 0], [], []], "par": 8}, {"level": 76, "capacity": 6, "tiers": 3, "mergeN": 4, "wallets": [[0, 1, 0, 1, 0, 1], [0, 0, 0, 1, 1, 1], [1, 0, 1, 0, 1, 0], [], [], []], "par": 10}, {"level": 77, "capacity": 6, "tiers": 3, "mergeN": 4, "wallets": [[1, 0, 1, 0, 0, 1], [0, 0, 1, 0, 1, 0], [0, 1, 1, 0, 1, 1], [], []], "par": 10}, {"level": 78, "capacity": 6, "tiers": 3, "mergeN": 4, "wallets": [[0, 1, 1, 0, 1, 0], [0, 0, 1, 0, 1, 0], [0, 0, 0, 1, 0, 1], [], [], []], "par": 11}, {"level": 79, "capacity": 6, "tiers": 3, "mergeN": 4, "wallets": [[1, 1, 0, 0, 1, 0], [0, 0, 0, 1, 0, 1], [1, 1, 0, 1, 1, 0], [], []], "par": 8}, {"level": 80, "capacity": 6, "tiers": 3, "mergeN": 4, "wallets": [[0, 0, 1, 0, 0, 0], [1, 0, 1, 0, 0, 1], [0, 0, 1, 0, 1, 0], [], [], []], "par": 9}, {"level": 81, "capacity": 6, "tiers": 3, "mergeN": 4, "wallets": [[0, 1, 0, 1, 0, 1], [0, 0, 0, 0, 1, 1], [0, 0, 0, 0, 0, 1], [], []], "par": 8}, {"level": 82, "capacity": 6, "tiers": 3, "mergeN": 4, "wallets": [[0, 1, 1, 0, 1, 0], [1, 0, 0, 0, 1, 0], [0, 0, 0, 0, 1, 0], [], [], []], "par": 8}, {"level": 83, "capacity": 6, "tiers": 3, "mergeN": 4, "wallets": [[0, 1, 0, 1, 0, 0], [1, 0, 0, 0, 1, 0], [0, 1, 0, 1, 1, 0], [], []], "par": 9}, {"level": 84, "capacity": 6, "tiers": 3, "mergeN": 4, "wallets": [[0, 0, 0, 1, 0, 0], [1, 0, 1, 0, 0, 0], [1, 0, 1, 0, 0, 1], [], [], []], "par": 8}, {"level": 85, "capacity": 6, "tiers": 3, "mergeN": 4, "wallets": [[0, 1, 1, 0, 1, 0], [1, 0, 0, 0, 0, 0], [0, 0, 1, 0, 0, 0], [], []], "par": 8}, {"level": 86, "capacity": 6, "tiers": 3, "mergeN": 4, "wallets": [[1, 1, 1, 0, 1, 0], [1, 0, 1, 0, 1, 0], [1, 0, 1, 1, 0, 0], [], [], []], "par": 10}, {"level": 87, "capacity": 6, "tiers": 3, "mergeN": 4, "wallets": [[1, 0, 0, 0, 0, 0], [0, 1, 0, 0, 0, 1], [1, 0, 0, 1, 0, 1], [], []], "par": 8}, {"level": 88, "capacity": 6, "tiers": 3, "mergeN": 4, "wallets": [[0, 0, 1, 1, 0, 1], [1, 0, 1, 1, 1, 0], [1, 0, 1, 0, 0, 0], [], [], []], "par": 8}, {"level": 89, "capacity": 6, "tiers": 3, "mergeN": 4, "wallets": [[0, 0, 0, 1, 0, 0], [0, 0, 1, 0, 1, 0], [0, 1, 0, 0, 0, 0], [], []], "par": 8}, {"level": 90, "capacity": 6, "tiers": 3, "mergeN": 4, "wallets": [[1, 0, 0, 0, 0, 1], [0, 1, 0, 0, 0, 0], [1, 0, 0, 1, 0, 1], [], [], []], "par": 8}, {"level": 91, "capacity": 6, "tiers": 3, "mergeN": 4, "wallets": [[1, 0, 0, 0, 1, 0], [0, 0, 0, 1, 0, 1], [0, 0, 1, 0, 0, 1], [], []], "par": 8}, {"level": 92, "capacity": 6, "tiers": 3, "mergeN": 4, "wallets": [[0, 0, 1, 0, 1, 0], [1, 0, 1, 0, 0, 0], [0, 1, 1, 0, 1, 0], [], [], []], "par": 10}, {"level": 93, "capacity": 6, "tiers": 3, "mergeN": 4, "wallets": [[0, 1, 0, 1, 1, 0], [0, 0, 1, 1, 0, 1], [0, 1, 0, 0, 0, 0], [], []], "par": 9}, {"level": 94, "capacity": 6, "tiers": 3, "mergeN": 4, "wallets": [[0, 1, 1, 0, 1, 0], [1, 0, 0, 1, 1, 0], [0, 1, 1, 0, 0, 0], [], [], []], "par": 8}, {"level": 95, "capacity": 6, "tiers": 3, "mergeN": 4, "wallets": [[0, 0, 0, 1, 0, 0], [1, 0, 1, 0, 1, 0], [1, 0, 0, 0, 0, 0], [], []], "par": 8}, {"level": 96, "capacity": 6, "tiers": 3, "mergeN": 4, "wallets": [[0, 1, 1, 0, 1, 0], [0, 0, 1, 0, 0, 0], [0, 0, 0, 0, 1, 0], [], [], []], "par": 8}, {"level": 97, "capacity": 6, "tiers": 3, "mergeN": 4, "wallets": [[1, 0, 0, 0, 0, 0], [0, 0, 0, 1, 0, 1], [0, 0, 1, 0, 0, 1], [], []], "par": 8}, {"level": 98, "capacity": 6, "tiers": 3, "mergeN": 4, "wallets": [[0, 0, 0, 1, 0, 0], [0, 0, 1, 1, 0, 1], [0, 1, 1, 0, 0, 1], [], [], []], "par": 8}, {"level": 99, "capacity": 6, "tiers": 3, "mergeN": 4, "wallets": [[1, 0, 0, 0, 0, 1], [0, 1, 1, 0, 1, 0], [0, 0, 0, 1, 0, 0], [0, 1, 0, 0, 1, 0], [], []], "par": 11}, {"level": 100, "capacity": 6, "tiers": 3, "mergeN": 4, "wallets": [[0, 0, 0, 1, 1, 0], [0, 0, 0, 1, 0, 0], [0, 1, 0, 0, 1, 0], [0, 1, 0, 1, 0, 0], [], []], "par": 11}, {"level": 101, "capacity": 6, "tiers": 3, "mergeN": 4, "wallets": [[0, 0, 1, 0, 1, 0], [0, 1, 1, 0, 0, 0], [0, 1, 0, 0, 1, 0], [1, 0, 1, 1, 1, 1], [], []], "par": 11}, {"level": 102, "capacity": 6, "tiers": 3, "mergeN": 4, "wallets": [[1, 0, 1, 0, 0, 1], [1, 0, 0, 1, 0, 1], [0, 0, 0, 1, 0, 0], [0, 0, 1, 0, 0, 1], [], []], "par": 11}, {"level": 103, "capacity": 6, "tiers": 3, "mergeN": 4, "wallets": [[0, 1, 0, 0, 1, 1], [1, 0, 0, 1, 0, 1], [0, 1, 0, 0, 1, 1], [0, 1, 0, 1, 0, 0], [], []], "par": 12}, {"level": 104, "capacity": 6, "tiers": 3, "mergeN": 4, "wallets": [[1, 0, 1, 0, 1, 1], [0, 0, 1, 1, 0, 1], [0, 0, 0, 1, 0, 0], [1, 0, 1, 0, 0, 1], [], []], "par": 11}, {"level": 105, "capacity": 6, "tiers": 3, "mergeN": 4, "wallets": [[0, 1, 0, 0, 0, 1], [0, 0, 1, 0, 1, 1], [1, 0, 1, 0, 0, 1], [0, 0, 1, 0, 1, 0], [], []], "par": 12}, {"level": 106, "capacity": 6, "tiers": 3, "mergeN": 4, "wallets": [[0, 1, 1, 0, 0, 1], [0, 0, 0, 1, 0, 1], [0, 1, 0, 0, 0, 0], [0, 1, 0, 1, 0, 0], [], []], "par": 11}, {"level": 107, "capacity": 6, "tiers": 3, "mergeN": 4, "wallets": [[0, 0, 0, 1, 0, 1], [0, 1, 0, 0, 1, 1], [0, 0, 1, 0, 1, 0], [0, 0, 0, 0, 1, 0], [], []], "par": 11}, {"level": 108, "capacity": 6, "tiers": 3, "mergeN": 4, "wallets": [[0, 0, 1, 0, 1, 0], [0, 0, 1, 0, 1, 0], [1, 1, 1, 1, 0, 0], [0, 0, 0, 1, 0, 0], [], []], "par": 11}, {"level": 109, "capacity": 6, "tiers": 3, "mergeN": 4, "wallets": [[1, 0, 0, 0, 1, 0], [0, 1, 0, 0, 0, 0], [0, 1, 0, 1, 0, 0], [1, 0, 1, 1, 0, 1], [], []], "par": 11}, {"level": 110, "capacity": 6, "tiers": 3, "mergeN": 4, "wallets": [[1, 0, 1, 0, 1, 0], [0, 1, 1, 0, 0, 0], [0, 1, 1, 0, 0, 0], [0, 1, 0, 0, 1, 0], [], []], "par": 11}, {"level": 111, "capacity": 6, "tiers": 3, "mergeN": 4, "wallets": [[0, 0, 0, 1, 0, 1], [0, 0, 0, 0, 1, 1], [0, 0, 1, 0, 1, 0], [0, 1, 1, 1, 0, 1], [], []], "par": 11}, {"level": 112, "capacity": 6, "tiers": 3, "mergeN": 4, "wallets": [[0, 1, 0, 0, 1, 0], [1, 0, 0, 0, 1, 0], [0, 1, 0, 0, 0, 0], [0, 0, 1, 0, 1, 0], [], []], "par": 11}, {"level": 113, "capacity": 6, "tiers": 3, "mergeN": 4, "wallets": [[0, 1, 1, 1, 0, 0], [0, 1, 0, 1, 0, 1], [0, 1, 1, 0, 0, 0], [0, 1, 1, 0, 0, 1], [], []], "par": 11}, {"level": 114, "capacity": 6, "tiers": 3, "mergeN": 4, "wallets": [[0, 1, 0, 1, 1, 0], [1, 0, 1, 0, 0, 1], [0, 0, 1, 0, 1, 0], [0, 0, 1, 0, 0, 1], [], []], "par": 13}, {"level": 115, "capacity": 6, "tiers": 3, "mergeN": 4, "wallets": [[0, 0, 0, 0, 1, 0], [1, 0, 1, 1, 0, 1], [0, 0, 1, 0, 1, 0], [0, 0, 1, 1, 1, 0], [], []], "par": 11}, {"level": 116, "capacity": 6, "tiers": 3, "mergeN": 4, "wallets": [[0, 1, 1, 1, 0, 0], [0, 1, 0, 1, 1, 0], [0, 0, 1, 0, 1, 0], [0, 0, 1, 0, 0, 1], [], []], "par": 12}, {"level": 117, "capacity": 6, "tiers": 3, "mergeN": 4, "wallets": [[1, 0, 1, 0, 0, 1], [0, 1, 0, 0, 0, 0], [1, 0, 0, 0, 0, 0], [0, 0, 0, 1, 0, 1], [], []], "par": 11}, {"level": 118, "capacity": 6, "tiers": 3, "mergeN": 4, "wallets": [[1, 0, 0, 0, 1, 0], [0, 0, 1, 0, 1, 0], [1, 0, 1, 0, 1, 0], [1, 1, 1, 0, 0, 1], [], []], "par": 12}, {"level": 119, "capacity": 6, "tiers": 3, "mergeN": 4, "wallets": [[0, 1, 0, 0, 1, 0], [0, 1, 0, 0, 0, 0], [0, 0, 1, 0, 0, 0], [0, 1, 0, 1, 1, 0], [], []], "par": 11}, {"level": 120, "capacity": 6, "tiers": 3, "mergeN": 4, "wallets": [[1, 0, 1, 0, 1, 0], [1, 0, 0, 0, 1, 0], [0, 0, 0, 0, 1, 1], [1, 0, 0, 1, 0, 1], [], []], "par": 11}]